pmath
