Metadata-Version: 1.1
Name: pmath
Version: 0.3
Summary: Bringing the math tools of Python to the command-line
Home-page: https://github.com/wackywendell/pmath
Author: Wendell Smith
Author-email: wackywendell@gmail.com
License: BSD
Keywords: math python console command-line bash
Platform: UNKNOWN
Classifier: Development Status :: 3 - Alpha
Classifier: Topic :: Scientific/Engineering :: Mathematics
Classifier: Topic :: Scientific/Engineering :: Physics
Classifier: Intended Audience :: Science/Research
Classifier: Operating System :: POSIX :: Linux
Classifier: Programming Language :: Python :: 2
Classifier: Programming Language :: Python :: 3
Classifier: License :: OSI Approved :: BSD License
